README.md
fastapi_accelerator/__init__.py
fastapi_accelerator/appstate.py
fastapi_accelerator/auth_jwt.py
fastapi_accelerator/cache.py
fastapi_accelerator/commands/__init__.py
fastapi_accelerator/commands/py2dantic.py
fastapi_accelerator/commands/tests/__init__.py
fastapi_accelerator/commands/tests/test_py2dantic.py
fastapi_accelerator/db/__init__.py
fastapi_accelerator/db/dborm.py
fastapi_accelerator/db/dbsession.py
fastapi_accelerator/exception.py
fastapi_accelerator/integration/__init__.py
fastapi_accelerator/integration/base_integration.py
fastapi_accelerator/integration/http_integration.py
fastapi_accelerator/integration/stability_patterns.py
fastapi_accelerator/middleware.py
fastapi_accelerator/paginator.py
fastapi_accelerator/pattern/__init__.py
fastapi_accelerator/pattern/pattern_alembic.py
fastapi_accelerator/pattern/pattern_fastapi.py
fastapi_accelerator/pattern/pattern_flask_admin.py
fastapi_accelerator/templates/docintegration.html
fastapi_accelerator/testutils/__init__.py
fastapi_accelerator/testutils/fixture_auth.py
fastapi_accelerator/testutils/fixture_base.py
fastapi_accelerator/testutils/fixture_db/__init__.py
fastapi_accelerator/testutils/fixture_db/apply_fixture.py
fastapi_accelerator/testutils/fixture_db/db.py
fastapi_accelerator/testutils/fixture_db/trace_sql.py
fastapi_accelerator/testutils/fixture_integration.py
fastapi_accelerator/testutils/utils.py
fastapi_accelerator/timezone.py
fastapi_accelerator/utils.py
fastapi_accelerator/viewset.py
fastapi_accelerator-0.0.5.dist-info/LICENSE
fastapi_accelerator-0.0.5.dist-info/METADATA
fastapi_accelerator-0.0.5.dist-info/WHEEL
fastapi_accelerator-0.0.5.dist-info/RECORD
