Metadata-Version: 2.1
Name: fastapi_accelerator
Version: 0.0.5
Summary: Ускоритель разработки для FastAPI, предоставляющий готовые решения и инструменты для быстрого создания веб-приложений
Home-page: https://github.com/denisxab/fastapi-accelerator
License: MIT
Keywords: fastapi,django,web-framework,api,rest,async,sqlalchemy,admin-panel
Author: Denis Kustov
Author-email: pro-progerkustov@yandex.ru
Requires-Python: >=3.9
Classifier: Framework :: FastAPI
Classifier: Intended Audience :: Developers
Classifier: License :: OSI Approved :: MIT License
Classifier: Operating System :: OS Independent
Classifier: Programming Language :: Python :: 3
Classifier: Programming Language :: Python :: 3.9
Classifier: Programming Language :: Python :: 3.10
Classifier: Programming Language :: Python :: 3.11
Classifier: Programming Language :: Python :: 3.12
Classifier: Topic :: Software Development :: Libraries :: Python Modules
Requires-Dist: alembic (>=1.13.2)
Requires-Dist: asyncpg (>=0.29.0)
Requires-Dist: fastapi (>=0.112.2)
Requires-Dist: flask-admin (>=1.6.1)
Requires-Dist: jinja2 (>=3.1.4,<4.0.0)
Requires-Dist: psycopg2-binary (>=2.9.9)
Requires-Dist: pyjwt (>=2.9.0)
Requires-Dist: python-multipart (>=0.0.9)
Requires-Dist: pytz (>=2024.1)
Requires-Dist: redis[asyncio] (>=5.0.8)
Requires-Dist: sqlalchemy (>=2.0.32)
Requires-Dist: uvicorn (>=0.30.6)
Project-URL: Repository, https://github.com/denisxab/fastapi-accelerator
